AUTHORS.rst
CONTRIBUTING.rst
HISTORY.rst
LICENSE
MANIFEST.in
README.rst
setup.py
django_reform.egg-info/PKG-INFO
django_reform.egg-info/SOURCES.txt
django_reform.egg-info/dependency_links.txt
django_reform.egg-info/not-zip-safe
django_reform.egg-info/requires.txt
django_reform.egg-info/top_level.txt
reform/__init__.py
reform/models.py
reform/static/js/reform.js
reform/templates/bootstrap_toolkit/field_prepend_append.html
reform/templates/bootstrap_toolkit/form.html
reform/templates/reform/base.html
reform/templates/reform/field.html
reform/templatetags/__init__.py
reform/templatetags/reform.py