Metadata-Version: 1.0
Name: django-reform
Version: 0.3.0
Summary: Control of widgets in templates sans BS.
Home-page: https://github.com/alixedi/django_reform
Author: Ali Zaidi
Author-email: alixedi@gmail.com
License: BSD
Keywords: django_reform
Platform: UNKNOWN
Classifier: Development Status :: 2 - Pre-Alpha
Classifier: Framework :: Django
Classifier: Intended Audience :: Developers
Classifier: License :: OSI Approved :: BSD License
Classifier: Natural Language :: English
Classifier: Programming Language :: Python :: 2
Classifier: Programming Language :: Python :: 2.6
Classifier: Programming Language :: Python :: 2.7
Classifier: Programming Language :: Python :: 3
Classifier: Programming Language :: Python :: 3.3
